list_sum.py
add_list_AK_311-0.0.3.dist-info/METADATA
add_list_AK_311-0.0.3.dist-info/WHEEL
add_list_AK_311-0.0.3.dist-info/top_level.txt
add_list_AK_311-0.0.3.dist-info/RECORD
