Metadata-Version: 2.1
Name: add_list_AK_311
Version: 0.0.3
Summary: adding a list
Author-email: AK <ak@test.com>
Requires-Python: >=3.8
